{"paper":"[\"Group\",{\"applyMatrix\":true,\"children\":[[\"Shape\",{\"applyMatrix\":false,\"matrix\":[1,0,0,1,75.7386,64.7386],\"clipMask\":true,\"type\":\"rectangle\",\"size\":[151.4772,129.4772],\"radius\":[0,0]}],[\"Group\",{\"applyMatrix\":true,\"children\":[[\"Group\",{\"applyMatrix\":true,\"data\":{\"isPaintingLayer\":true},\"children\":[[\"Path\",{\"applyMatrix\":false,\"segments\":[[[75.9386,105.6386],[4.9,-3.6],[-0.1,0]],[[75.7386,105.7386],[0.1,0],[0,0]],[75.7386,105.7386],[[75.5386,105.6386],[0.1,0],[-4.9,-3.6]],[[25.8386,30.5386],[-18.3,25.2],[18.2,-25.2]],[[75.6386,34.9386],[-2.3,-2.2],[2.4,-2.3]],[[125.4386,30.5386],[-18.2,-25.2],[18.5,25.2]]],\"closed\":true,\"fillColor\":[1,1,1],\"strokeColor\":[1,1,1],\"strokeWidth\":7.4772,\"strokeCap\":\"round\",\"strokeJoin\":\"round\"}],[\"Group\",{\"applyMatrix\":true,\"children\":[[\"Path\",{\"applyMatrix\":false,\"segments\":[[75.7386,4.7386],[75.7386,3.7386]],\"fillColor\":[1,1,1],\"strokeColor\":[1,1,1],\"strokeWidth\":7.4772,\"strokeCap\":\"round\",\"strokeJoin\":\"round\"}],[\"Path\",{\"applyMatrix\":false,\"segments\":[[75.7386,125.7386],[75.7386,124.7386]],\"fillColor\":[1,1,1],\"strokeColor\":[1,1,1],\"strokeWidth\":7.4772,\"strokeCap\":\"round\",\"strokeJoin\":\"round\"}]]}],[\"Group\",{\"applyMatrix\":true,\"children\":[[\"Path\",{\"applyMatrix\":false,\"segments\":[[146.7386,64.7386],[147.7386,64.7386]],\"fillColor\":[1,1,1],\"strokeColor\":[1,1,1],\"strokeWidth\":7.4772,\"strokeCap\":\"round\",\"strokeJoin\":\"round\"}],[\"Path\",{\"applyMatrix\":false,\"segments\":[[3.7386,64.7386],[4.7386,64.7386]],\"fillColor\":[1,1,1],\"strokeColor\":[1,1,1],\"strokeWidth\":7.4772,\"strokeCap\":\"round\",\"strokeJoin\":\"round\"}],[\"Group\",{\"applyMatrix\":true,\"children\":[[\"Path\",{\"applyMatrix\":false,\"segments\":[[130.7386,9.8386],[129.9386,10.5386]],\"fillColor\":[1,1,1],\"strokeColor\":[1,1,1],\"strokeWidth\":7.4772,\"strokeCap\":\"round\",\"strokeJoin\":\"round\"}],[\"Path\",{\"applyMatrix\":false,\"segments\":[[28.8386,111.6386],[29.5386,110.9386]],\"fillColor\":[1,1,1],\"strokeColor\":[1,1,1],\"strokeWidth\":7.4772,\"strokeCap\":\"round\",\"strokeJoin\":\"round\"}]]}],[\"Group\",{\"applyMatrix\":true,\"children\":[[\"Path\",{\"applyMatrix\":false,\"segments\":[[21.5386,10.5386],[20.8386,9.8386]],\"fillColor\":[1,1,1],\"strokeColor\":[1,1,1],\"strokeWidth\":7.4772,\"strokeCap\":\"round\",\"strokeJoin\":\"round\"}],[\"Path\",{\"applyMatrix\":false,\"segments\":[[122.7386,111.6386],[121.9386,110.9386]],\"fillColor\":[1,1,1],\"strokeColor\":[1,1,1],\"strokeWidth\":7.4772,\"strokeCap\":\"round\",\"strokeJoin\":\"round\"}]]}]]}]]}]]}]]}]","measurements":{"width":223.86341857910156,"height":250.00172424316406,"x":-0.499996542930603,"y":-0.49999040365219116}}